Workbook

Sheet Suppliers
A1: Supplier_ID | B1: Supplier_Name | C1: Country | D1: Payment_Terms
A2: SUP001 | B2: ABC Office Supplies | C2: USA | D2: 30
A3: SUP002 | B3: Global IT Services | C3: UK | D3: 45
A4: SUP003 | B4: Bright Marketing | C4: Canada | D4: 30
A5: SUP004 | B5: Delta Logistics | C5: Germany | D5: 60
A6: SUP005 | B6: Tech Hardware Ltd | C6: USA | D6: 30
A7: SUP006 | B7: Green Energy Co | C7: Netherlands | D7: 45
A8: SUP007 | B8: Secure Systems | C8: UK | D8: 30
A9: SUP008 | B9: Rapid Transport | C9: France | D9: 60
A10: SUP009 | B10: Apex Consulting | C10: USA | D10: 30
A11: SUP010 | B11: Smart Packaging | C11: Italy | D11: 45
A12: SUP011 | B12: Metro Utilities Ltd | C12: UK | D12: 30
A13: SUP012 | B13: CloudWorks Software Ltd | C13: Ireland | D13: 30
... A19: SUP018 | B19: MediaEdge Marketing Ltd | C19: France | D19: 45

Sheet Customers
A1: Customer_ID | B1: Customer_Name | C1: Country | D1: Credit_Terms
A2: CUS001 | B2: Blue Retail | C2: USA | D2: 30
A3: CUS002 | B3: Nova Electronics | C3: UK | D3: 45
A4: CUS003 | B4: Urban Stores | C4: Canada | D4: 30
A5: CUS004 | B5: Prime Wholesale | C5: Germany | D5: 60
A6: CUS005 | B6: City Market | C6: USA | D6: 30
A7: CUS006 | B7: Mega Distributors | C7: France | D7: 45
A8: CUS007 | B8: Smart Retail | C8: UK | D8: 30
A9: CUS008 | B9: Value Stores | C9: Netherlands | D9: 60
A10: CUS009 | B10: Retail Hub | C10: USA | D10: 30
A11: CUS010 | B11: Tech Bazaar | C11: Italy | D11: 45
A12: CUS011 | B12: BluePeak Retail Group | C12: UK | D12: 30
A13: CUS012 | B13: Nova Wholesale Ltd | C13: Germany | D13: 45
... A15: CUS014 | B15: ClearView Corporate Ltd | C15: USA | D15: 60

Sheet Invoices
A1: Invoice_ID | B1: Date | C1: Type | D1: Party_ID | E1: Amount | F1: Due_Date | G1: Status | H1: Party_Name | I1: Terms | J1: Paid_Amount | K1: Balance | L1: Days_Overdue | N1: Report_Date
A2: INV001 | B2: 45292 | C2: AP | D2: SUP001 | E2: 1200 | F2: 45322 | G2: =IF(K2=0,"Closed",IF(J2=0,"Open","Partially Paid")) -> Closed | H2: =IF(C2="AP",_xlfn.XLOOKUP(D2,Suppliers!A:A,Suppliers!B:B,""),_xlfn.XLOOKUP(D2,Customers!A:A,Customers!B:B,"")) -> ABC Office Supplies | I2: =IF(C2="AP",_xlfn.XLOOKUP(D2,Suppliers!A:A,Suppliers!D:D,""),_xlfn.XLOOKUP(D2,Customers!A:A,Customers!D:D,"")) -> 30 | J2: =SUMIF(Payments!C:C,A2,Payments!D:D) -> 1200 | K2: 0 | L2: =IF(K2=0,0,$N$2-F2) -> 0 | N2: 45346
A3: INV002 | B3: 45293 | C3: AR | D3: CUS001 | E3: 2500 | F3: 45323 | G3: =IF(K3=0,"Closed",IF(J3=0,"Open","Partially Paid")) -> Partially Paid | H3: =IF(C3="AP",_xlfn.XLOOKUP(D3,Suppliers!A:A,Suppliers!B:B,""),_xlfn.XLOOKUP(D3,Customers!A:A,Customers!B:B,"")) -> Blue Retail | I3: =IF(C3="AP",_xlfn.XLOOKUP(D3,Suppliers!A:A,Suppliers!D:D,""),_xlfn.XLOOKUP(D3,Customers!A:A,Customers!D:D,"")) -> 30 | J3: =SUMIF(Payments!C:C,A3,Payments!D:D) -> 1000 | K3: =E3-J3 -> 1500 | L3: =IF(K3=0,0,$N$2-F3) -> 23
A4: INV003 | B4: 45294 | C4: AP | D4: SUP003 | E4: 800 | F4: 45324 | G4: =IF(K4=0,"Closed",IF(J4=0,"Open","Partially Paid")) -> Closed | H4: =IF(C4="AP",_xlfn.XLOOKUP(D4,Suppliers!A:A,Suppliers!B:B,""),_xlfn.XLOOKUP(D4,Customers!A:A,Customers!B:B,"")) -> Bright Marketing | I4: =IF(C4="AP",_xlfn.XLOOKUP(D4,Suppliers!A:A,Suppliers!D:D,""),_xlfn.XLOOKUP(D4,Customers!A:A,Customers!D:D,"")) -> 30 | J4: =SUMIF(Payments!C:C,A4,Payments!D:D) -> 800 | K4: =E4-J4 -> 0 | L4: =IF(K4=0,0,$N$2-F4) -> 0
A5: INV004 | B5: 45296 | C5: AR | D5: CUS004 | E5: 3200 | F5: 45326 | G5: =IF(K5=0,"Closed",IF(J5=0,"Open","Partially Paid")) -> Closed | H5: =IF(C5="AP",_xlfn.XLOOKUP(D5,Suppliers!A:A,Suppliers!B:B,""),_xlfn.XLOOKUP(D5,Customers!A:A,Customers!B:B,"")) -> Prime Wholesale | I5: =IF(C5="AP",_xlfn.XLOOKUP(D5,Suppliers!A:A,Suppliers!D:D,""),_xlfn.XLOOKUP(D5,Customers!A:A,Customers!D:D,"")) -> 60 | J5: =SUMIF(Payments!C:C,A5,Payments!D:D) -> 3200 | K5: =E5-J5 -> 0 | L5: =IF(K5=0,0,$N$2-F5) -> 0
A6: INV005 | B6: 45297 | C6: AP | D6: SUP005 | E6: 1500 | F6: 45327 | G6: =IF(K6=0,"Closed",IF(J6=0,"Open","Partially Paid")) -> Partially Paid | H6: =IF(C6="AP",_xlfn.XLOOKUP(D6,Suppliers!A:A,Suppliers!B:B,""),_xlfn.XLOOKUP(D6,Customers!A:A,Customers!B:B,"")) -> Tech Hardware Ltd | I6: =IF(C6="AP",_xlfn.XLOOKUP(D6,Suppliers!A:A,Suppliers!D:D,""),_xlfn.XLOOKUP(D6,Customers!A:A,Customers!D:D,"")) -> 30 | J6: =SUMIF(Payments!C:C,A6,Payments!D:D) -> 500 | K6: =E6-J6 -> 1000 | L6: =IF(K6=0,0,$N$2-F6) -> 19
A7: INV006 | B7: 45299 | C7: AR | D7: CUS002 | E7: 2100 | F7: 45329 | G7: =IF(K7=0,"Closed",IF(J7=0,"Open","Partially Paid")) -> Closed | H7: =IF(C7="AP",_xlfn.XLOOKUP(D7,Suppliers!A:A,Suppliers!B:B,""),_xlfn.XLOOKUP(D7,Customers!A:A,Customers!B:B,"")) -> Nova Electronics | I7: =IF(C7="AP",_xlfn.XLOOKUP(D7,Suppliers!A:A,Suppliers!D:D,""),_xlfn.XLOOKUP(D7,Customers!A:A,Customers!D:D,"")) -> 45 | J7: =SUMIF(Payments!C:C,A7,Payments!D:D) -> 2100 | K7: =E7-J7 -> 0 | L7: =IF(K7=0,0,$N$2-F7) -> 0
A8: INV007 | B8: 45300 | C8: AP | D8: SUP008 | E8: 900 | F8: 45332 | G8: =IF(K8=0,"Closed",IF(J8=0,"Open","Partially Paid")) -> Open | H8: =IF(C8="AP",_xlfn.XLOOKUP(D8,Suppliers!A:A,Suppliers!B:B,""),_xlfn.XLOOKUP(D8,Customers!A:A,Customers!B:B,"")) -> Rapid Transport | I8: =IF(C8="AP",_xlfn.XLOOKUP(D8,Suppliers!A:A,Suppliers!D:D,""),_xlfn.XLOOKUP(D8,Customers!A:A,Customers!D:D,"")) -> 60 | J8: =SUMIF(Payments!C:C,A8,Payments!D:D) -> 0 | K8: =E8-J8 -> 900 | L8: =IF(K8=0,0,$N$2-F8) -> 14
A9: INV008 | B9: 45301 | C9: AR | D9: CUS006 | E9: 1800 | F9: 45333 | G9: =IF(K9=0,"Closed",IF(J9=0,"Open","Partially Paid")) -> Closed | H9: =IF(C9="AP",_xlfn.XLOOKUP(D9,Suppliers!A:A,Suppliers!B:B,""),_xlfn.XLOOKUP(D9,Customers!A:A,Customers!B:B,"")) -> Mega Distributors | I9: =IF(C9="AP",_xlfn.XLOOKUP(D9,Suppliers!A:A,Suppliers!D:D,""),_xlfn.XLOOKUP(D9,Customers!A:A,Customers!D:D,"")) -> 45 | J9: =SUMIF(Payments!C:C,A9,Payments!D:D) -> 1800 | K9: =E9-J9 -> 0 | L9: =IF(K9=0,0,$N$2-F9) -> 0
A10: INV009 | B10: 45302 | C10: AP | D10: SUP002 | E10: 2400 | F10: 45332 | G10: =IF(K10=0,"Closed",IF(J10=0,"Open","Partially Paid")) -> Partially Paid | H10: =IF(C10="AP",_xlfn.XLOOKUP(D10,Suppliers!A:A,Suppliers!B:B,""),_xlfn.XLOOKUP(D10,Customers!A:A,Customers!B:B,"")) -> Global IT Services | I10: =IF(C10="AP",_xlfn.XLOOKUP(D10,Suppliers!A:A,Suppliers!D:D,""),_xlfn.XLOOKUP(D10,Customers!A:A,Customers!D:D,"")) -> 45 | J10: =SUMIF(Payments!C:C,A10,Payments!D:D) -> 1000 | K10: =E10-J10 -> 1400 | L10: =IF(K10=0,0,$N$2-F10) -> 14
A11: INV010 | B11: 45303 | C11: AR | D11: CUS003 | E11: 2700 | F11: 45333 | G11: =IF(K11=0,"Closed",IF(J11=0,"Open","Partially Paid")) -> Closed | H11: =IF(C11="AP",_xlfn.XLOOKUP(D11,Suppliers!A:A,Suppliers!B:B,""),_xlfn.XLOOKUP(D11,Customers!A:A,Customers!B:B,"")) -> Urban Stores | I11: =IF(C11="AP",_xlfn.XLOOKUP(D11,Suppliers!A:A,Suppliers!D:D,""),_xlfn.XLOOKUP(D11,Customers!A:A,Customers!D:D,"")) -> 30 | J11: =SUMIF(Payments!C:C,A11,Payments!D:D) -> 2700 | K11: =E11-J11 -> 0 | L11: =IF(K11=0,0,$N$2-F11) -> 0
A12: INV011 | B12: 45304 | C12: AP | D12: SUP004 | E12: 3600 | F12: 45364 | G12: Open | H12: Delta Logistics | I12: 60 | J12: 0 | K12: 3600 | L12: 0
A13: INV012 | B13: 45305 | C13: AR | D13: CUS005 | E13: 1950 | F13: 45335 | G13: Partially Paid | H13: City Market | I13: 30 | J13: 800 | K13: 1150 | L13: 11
A14: INV013 | B14: 45306 | C14: AP | D14: SUP006 | E14: 2200 | F14: 45351 | G14: Open | H14: Green Energy Co | I14: 45 | J14: 0 | K14: 2200 | L14: 0
A15: INV014 | B15: 45307 | C15: AR | D15: CUS008 | E15: 4100 | F15: 45367 | G15: Open | H15: Value Stores | I15: 60 | J15: 0 | K15: 4100 | L15: 0
A16: INV015 | B16: 45308 | C16: AP | D16: SUP011 | E16: 1300 | F16: 45338 | G16: Closed | H16: Metro Utilities Ltd | I16: 30 | J16: 1300 | K16: 0 | L16: 0
A17: INV016 | B17: 45309 | C17: AR | D17: CUS011 | E17: 2850 | F17: 45339 | G17: Partially Paid | H17: BluePeak Retail Group | I17: 30 | J17: 1000 | K17: 1850 | L17: 7
A18: INV017 | B18: 45310 | C18: AP | D18: SUP012 | E18: 950 | F18: 45340 | G18: Open | H18: CloudWorks Software Ltd | I18: 30 | J18: 0 | K18: 950 | L18: 6
A19: INV018 | B19: 45311 | C19: AR | D19: CUS012 | E19: 3750 | F19: 45356 | G19: Open | H19: Nova Wholesale Ltd | I19: 45 | J19: 0 | K19: 3750 | L19: 0
A20: INV019 | B20: 45313 | C20: AP | D20: SUP013 | E20: 2600 | F20: 45358 | G20: Partially Paid | H20: Prime Logistics Services | I20: 45 | J20: 1000 | K20: 1600 | L20: 0
A21: INV020 | B21: 45314 | C21: AR | D21: CUS013 | E21: 1650 | F21: 45344 | G21: Closed | H21: Horizon Online Stores | I21: 30 | J21: 1650 | K21: 0 | L21: 0
A22: INV021 | B22: 45315 | C22: AP | D22: SUP014 | E22: 1100 | F22: 45345 | G22: Open | H22: BrightClean Facilities | I22: 30 | J22: 0 | K22: 1100 | L22: 1
A23: INV022 | B23: 45316 | C23: AR | D23: CUS014 | E23: 5200 | F23: 45376 | G23: Open | H23: ClearView Corporate Ltd | I23: 60 | J23: 0 | K23: 5200 | L23: 0
... A81: INV080 | B81: 45324 | C81: AP | D81: SUP012 | E81: 1500 | F81: 45354 | G81: Closed | H81: CloudWorks Software Ltd | I81: 30 | J81: 1500 | K81: 0 | L81: 0
A82: INV081 | B82: 45325 | C82: AP | D82: SUP013 | E82: 3250 | F82: 45370 | G82: Open | H82: Prime Logistics Services | I82: =IF(C82="AP",_xlfn.XLOOKUP(D82,Suppliers!A:A,Suppliers!D:D,""),_xlfn.XLOOKUP(D82,Customers!A:A,Customers!D:D,"")) -> 45 | J82: =SUMIF(Payments!C:C,A82,Payments!D:D) -> 0 | K82: =E82-J82 -> 3250 | L82: 0
A83: INV082 | B83: 45326 | C83: AR | D83: CUS010 | E83: 2900 | F83: 45371 | G83: Open | H83: Tech Bazaar | I83: 45 | J83: 0 | K83: 2900 | L83: 0
A84: INV083 | B84: 45327 | C84: AP | D84: SUP014 | E84: 1300 | F84: 45357 | G84: Partially Paid | H84: BrightClean Facilities | I84: 30 | J84: 500 | K84: 800 | L84: 0
A85: INV084 | B85: 45328 | C85: AR | D85: CUS011 | E85: 3750 | F85: 45358 | G85: Closed | H85: BluePeak Retail Group | I85: 30 | J85: 3750 | K85: 0 | L85: 0
A86: INV085 | B86: 45329 | C86: AP | D86: SUP015 | E86: 4950 | F86: 45389 | G86: Open | H86: Shield Insurance Brokers | I86: 60 | J86: 0 | K86: 4950 | L86: 0
A87: INV086 | B87: 45330 | C87: AP | D87: SUP016 | E87: 1600 | F87: 45360 | G87: Closed | H87: Apex Professional Services | I87: 30 | J87: 1600 | K87: 0 | L87: 0
A88: INV087 | B88: 45331 | C88: AR | D88: CUS012 | E88: 4400 | F88: 45376 | G88: Partially Paid | H88: Nova Wholesale Ltd | I88: 45 | J88: 1800 | K88: 2600 | L88: 0
A89: INV088 | B89: 45332 | C89: AP | D89: SUP017 | E89: 850 | F89: 45362 | G89: Open | H89: GreenOffice Supplies | I89: 30 | J89: 0 | K89: 850 | L89: 0
A90: INV089 | B90: 45333 | C90: AR | D90: CUS013 | E90: 2200 | F90: 45363 | G90: Open | H90: Horizon Online Stores | I90: 30 | J90: 0 | K90: 2200 | L90: 0
A91: INV090 | B91: 45334 | C91: AR | D91: CUS014 | E91: 5800 | F91: 45394 | G91: Partially Paid | H91: ClearView Corporate Ltd | I91: 60 | J91: 2000 | K91: 3800 | L91: 0
A92: INV091 | B92: 45335 | C92: AP | D92: SUP018 | E92: 2450 | F92: 45380 | G92: Open | H92: MediaEdge Marketing Ltd | I92: 45 | J92: 0 | K92: 2450 | L92: 0
A93: INV092 | B93: 45336 | C93: AR | D93: CUS001 | E93: 3600 | F93: 45366 | G93: Open | H93: Blue Retail | I93: 30 | J93: 0 | K93: 3600 | L93: 0
A94: INV093 | B94: 45337 | C94: AP | D94: SUP001 | E94: 1250 | F94: 45367 | G94: Closed | H94: ABC Office Supplies | I94: 30 | J94: 1250 | K94: 0 | L94: 0
... A111: INV110 | B111: 45303 | C111: AR | D111: CUS010 | E111: 3400 | F111: 45348 | G111: Open | H111: Tech Bazaar | I111: 45 | J111: 0 | K111: 3400 | L111: 0

Sheet Payments
A1: Payment_ID | B1: Date | C1: Invoice_ID | D1: Amount_Paid | E1: Method
A2: PAY001 | B2: 45306 | C2: INV001 | D2: 1200 | E2: Bank
A3: PAY002 | B3: 45311 | C3: INV002 | D3: 1000 | E3: Bank
A4: PAY003 | B4: 45316 | C4: INV003 | D4: 800 | E4: Bank
A5: PAY004 | B5: 45319 | C5: INV004 | D5: 3200 | E5: Bank
A6: PAY005 | B6: 45321 | C6: INV005 | D6: 500 | E6: Bank
A7: PAY006 | B7: 45324 | C7: INV006 | D7: 2100 | E7: Bank
A8: PAY007 | B8: 45327 | C8: INV008 | D8: 1800 | E8: Bank
A9: PAY008 | B9: 45330 | C9: INV009 | D9: 1000 | E9: Bank
A10: PAY009 | B10: 45332 | C10: INV010 | D10: 2700 | E10: Bank
A11: PAY010 | B11: 45337 | C11: INV012 | D11: 800 | E11: Bank
A12: PAY011 | B12: 45341 | C12: INV015 | D12: 1300 | E12: Bank
A13: PAY012 | B13: 45342 | C13: INV016 | D13: 1000 | E13: Bank
... A61: PAY060 | B61: 45346 | C61: INV108 | D61: 1950 | E61: Bank

Sheet Cashbook
A1: Date | B1: Description | C1: Type | D1: Debit | E1: Credit | F1: Balance
A2: 45292 | B2: Opening Balance | C2: Opening | D2: 5000 | E2: 0 | F2: =D2-E2 -> 5000
A3: 45306 | B3: Payment to supplier for INV001 | C3: Payment | D3: 0 | E3: 1200 | F3: =F2+D3-E3 -> 3800
A4: 45311 | B4: Payment received for INV002 | C4: Receipt | D4: 1000 | E4: 0 | F4: =F3+D4-E4 -> 4800
A5: 45316 | B5: Payment to supplier INV003 | C5: Payment | D5: 0 | E5: 800 | F5: =F4+D5-E5 -> 4000
A6: 45319 | B6: Payment received for INV004 | C6: Receipt | D6: 3200 | E6: 0 | F6: =F5+D6-E6 -> 7200
A7: 45321 | B7: Payment to supplier INV005 | C7: Payment | D7: 0 | E7: 500 | F7: =F6+D7-E7 -> 6700
A8: 45324 | B8: Payment received for INV006 | C8: Receipt | D8: 2100 | E8: 0 | F8: =F7+D8-E8 -> 8800
A9: 45327 | B9: Payment received for INV008 | C9: Receipt | D9: 1800 | E9: 0 | F9: =F8+D9-E9 -> 10600
A10: 45330 | B10: Payment to supplier INV009 | C10: Payment | D10: 0 | E10: 1000 | F10: =F9+D10-E10 -> 9600
A11: 45332 | B11: Payment received for INV010 | C11: Receipt | D11: 2700 | E11: 0 | F11: =F10+D11-E11 -> 12300
A12: 45337 | B12: Payment received for INV012 | C12: Receipt | D12: 800 | E12: 0 | F12: =F11+D12-E12 -> 13100
A13: 45341 | B13: Payment to supplier for INV015 | C13: Payment | D13: 0 | E13: 1300 | F13: =F12+D13-E13 -> 11800
A14: 45342 | B14: Payment received for INV016 | C14: Receipt | D14: 1000 | E14: 0 | F14: =F13+D14-E14 -> 12800
... A62: 45346 | B62: Payment received for INV108 | C62: Receipt | D62: 1950 | E62: 0 | F62: =F61+D62-E62 -> 23600

Sheet AP_Aging
A1: Supplier_ID | B1: Supplier_Name | C1: Invoice_ID | D1: Due_Date | E1: Balance | F1: Days_Overdue | G1: Age_Bucket
A2: SUP005 | B2: Tech Hardware Ltd | C2: INV005 | D2: 45327 | E2: 1000 | F2: 19 | G2: 1-30 Days
A3: SUP008 | B3: Rapid Transport | C3: INV007 | D3: 45332 | E3: 900 | F3: 14 | G3: 1-30 Days
A4: SUP002 | B4: Global IT Services | C4: INV009 | D4: 45332 | E4: 1400 | F4: 14 | G4: 1-30 Days
A5: SUP004 | B5: Delta Logistics | C5: INV011 | D5: 45364 | E5: 3600 | F5: 0 | G5: Current
A6: SUP006 | B6: Green Energy Co | C6: INV013 | D6: 45351 | E6: 2200 | F6: 0 | G6: Current
A7: SUP012 | B7: CloudWorks Software Ltd | C7: INV017 | D7: 45340 | E7: 950 | F7: 6 | G7: 1-30 Days
A8: SUP013 | B8: Prime Logistics Services | C8: INV019 | D8: 45358 | E8: 1600 | F8: 0 | G8: Current
A9: SUP014 | B9: BrightClean Facilities | C9: INV021 | D9: 45345 | E9: 1100 | F9: 1 | G9: 1-30 Days
A10: SUP016 | B10: Apex Professional Services | C10: INV025 | D10: 45350 | E10: 1750 | F10: 0 | G10: Current
A11: SUP017 | B11: GreenOffice Supplies | C11: INV027 | D11: 45352 | E11: 700 | F11: 0 | G11: Current
A12: SUP018 | B12: MediaEdge Marketing Ltd | C12: INV029 | D12: 45369 | E12: 2150 | F12: 0 | G12: Current
A13: SUP001 | B13: ABC Office Supplies | C13: INV031 | D13: 45356 | E13: 1450 | F13: 0 | G13: Current
... A45: SUP010 | B45: Smart Packaging | C45: INV109 | D45: 45347 | E45: 2900 | F45: 0 | G45: Current

Sheet AR_Aging
A1: Customer_ID | B1: Customer_Name | C1: Invoice_ID | D1: Due_Date | E1: Balance | F1: Days_Overdue | G1: Age_Bucket
A2: CUS001 | B2: Blue Retail | C2: INV002 | D2: 45323 | E2: 1500 | F2: 23 | G2: 1-30 Days
A3: CUS005 | B3: City Market | C3: INV012 | D3: 45335 | E3: 1150 | F3: 11 | G3: 1-30 Days
A4: CUS008 | B4: Value Stores | C4: INV014 | D4: 45367 | E4: 4100 | F4: 0 | G4: Current
A5: CUS011 | B5: BluePeak Retail Group | C5: INV016 | D5: 45339 | E5: 1850 | F5: 7 | G5: 1-30 Days
A6: CUS012 | B6: Nova Wholesale Ltd | C6: INV018 | D6: 45356 | E6: 3750 | F6: 0 | G6: Current
A7: CUS014 | B7: ClearView Corporate Ltd | C7: INV022 | D7: 45376 | E7: 5200 | F7: 0 | G7: Current
A8: CUS004 | B8: Prime Wholesale | C8: INV024 | D8: 45378 | E8: 1500 | F8: 0 | G8: Current
A9: CUS007 | B9: Smart Retail | C9: INV028 | D9: 45353 | E9: 2200 | F9: 0 | G9: Current
A10: CUS001 | B10: Blue Retail | C10: INV033 | D10: 45358 | E10: 3100 | F10: 0 | G10: Current
A11: CUS002 | B11: Nova Electronics | C11: INV035 | D11: 45375 | E11: 1600 | F11: 0 | G11: Current
A12: CUS003 | B12: Urban Stores | C12: INV038 | D12: 45363 | E12: 2250 | F12: 0 | G12: Current
A13: CUS004 | B13: Prime Wholesale | C13: INV040 | D13: 45395 | E13: 4800 | F13: 0 | G13: Current
... A36: CUS010 | B36: Tech Bazaar | C36: INV110 | D36: 45348 | E36: 3400 | F36: 0 | G36: Current

Sheet Summary
A1: Finance Operations Summary
A3: Total Invoices | B3: =COUNTA(Invoices!A:A)-1 -> 110
A4: Total Invoice Amount | B4: =SUM(Invoices!E:E) -> 293025
A5: Total Paid Amount | B5: =SUM(Invoices!J:J) -> 109300
A6: Total Outstanding Balance | B6: =SUM(Invoices!K:K) -> 183725
A7: Open Invoices | B7: =COUNTIF(Invoices!G:G,"Open") -> 50
A8: Partially Paid Invoices | B8: =COUNTIF(Invoices!G:G,"Partially Paid") -> 29
A9: Closed Invoices | B9: =COUNTIF(Invoices!G:G,"Closed") -> 31
A11: Total AP Outstanding | B11: =SUM(AP_Aging!E:E) -> 87475
A12: Total AR Outstanding | B12: =SUM(AR_Aging!E:E) -> 96250

Sheet Data_Source_Assumptions
A1: Area | B1: Explanation
A2: Project Title | B2: Tesco 2024 Finance Operations & Month-End Reporting Pack
A3: Company Reference | B3: Tesco PLC
A4: Source Document | B4: Tesco PLC Annual Report and Financial Statements 2024
A5: Source Type | B5: Public annual report / financial statement data
A6: Source Year | B6: 2024
A7: Tesco Reporting Date | B7: 45346
A8: Project Completion Date | B8: 46082
A9: Business Context | B9: Tesco is used as the real-company reference for this finance operations model
A10: Public Tesco Data Used | B10: Group sales, statutory revenue, business overview, financial statement context, payables/receivables/cash reference
A11: Transaction-Level Data | B11: Invoice-level AP, AR, payments, cashbook, and aging records are modelled for portfolio analysis
A12: Reason for Modelling | B12: Tesco’s public annual report does not disclose individual supplier invoices, customer invoices, or bank-level payment records
A13: Confidentiality Statement | B13: No confidential Tesco internal invoice, supplier, customer, payroll, or bank data is used
A14: Workbook Scope | B14: Accounts payable, accounts receivable, payments, cashbook, AP aging, AR aging, summary reporting, journals, accruals, prepayments, controls, and dashboard
A15: Tools Used | B15: Excel Tables, XLOOKUP, SUMIFS, PivotTables, conditional formatting, control checks
A16: Recruiter Explanation | B16: The project uses Tesco 2024 public financial data as a business reference, with modelled transaction-level finance operations data created to demonstrate practical AP, AR, cashbook, aging, and month-end reporting skills

Sheet Control_Checks sheet
A1: Check | B1: Formula_Result | C1: Status
A2: Total invoices = 110 | B2: =COUNTA(Invoices!A:A)-1 -> 110 | C2: =IF(B2=110,"PASS","FAIL") -> PASS
A3: Total suppliers = 18 | B3: =COUNTA(Suppliers!A:A)-1 -> 18 | C3: =IF(B3=18,"PASS","FAIL") -> PASS
A4: Total customers = 14 | B4: =COUNTA(Customers!A:A)-1 -> 14 | C4: =IF(B4=14,"PASS","FAIL") -> PASS
A5: Payment records = 60 | B5: =COUNTA(Payments!A:A)-1 -> 60 | C5: =IF(B5=60,"PASS","FAIL") -> PASS
A6: Invoice amount = paid + balance | B6: =SUM(Invoices!E:E)-SUM(Invoices!J:J)-SUM(Invoices!K:K) -> 0 | C6: =IF(ROUND(B6,2)=0,"PASS","FAIL") -> PASS
A7: AP aging total = AP outstanding | B7: =SUM(AP_Aging!E:E)-SUMIFS(Invoices!K:K,Invoices!C:C,"AP") -> 0 | C7: =IF(ROUND(B7,2)=0,"PASS","FAIL") -> PASS
A8: AR aging total = AR outstanding | B8: =SUM(AR_Aging!E:E)-SUMIFS(Invoices!K:K,Invoices!C:C,"AR") -> 0 | C8: =IF(ROUND(B8,2)=0,"PASS","FAIL") -> PASS
A9: AP + AR outstanding = total outstanding | B9: =SUM(AP_Aging!E:E)+SUM(AR_Aging!E:E)-SUM(Invoices!K:K) -> 0 | C9: =IF(ROUND(B9,2)=0,"PASS","FAIL") -> PASS
A10: Cashbook closing balance = 23,600 | B10: {=LOOKUP(2,1/(Cashbook!F:F<>""),Cashbook!F:F)} -> 23600 | C10: =IF(B10=23600,"PASS","FAIL") -> PASS
A11: No negative balances | B11: =COUNTIF(Invoices!K:K,"<0") -> 0 | C11: =IF(B11=0,"PASS","FAIL") -> PASS
A12: No missing party IDs | B12: =COUNTBLANK(Invoices!D:D)-COUNTBLANK(Invoices!A:A) -> 0 | C12: =IF(B12=0,"PASS","FAIL") -> PASS
A13: No duplicate invoice IDs | B13: =COUNTA(Invoices!A2:A111)-COUNTA(_xlfn.UNIQUE(Invoices!A2:A111)) -> 0 | C13: =IF(B13=0,"PASS","FAIL") -> PASS
A14: Journal debits = journal credits | B14: =SUM(Journal_Entries!E:E)-SUM(Journal_Entries!F:F) -> 0 | C14: =IF(ROUND(B14,2)=0,"PASS","FAIL") -> PASS
A15: Accruals total = 11,200 | B15: =SUM(Accruals_Schedule!F2:F6) -> 11200 | C15: =IF(B15=11200,"PASS","FAIL") -> PASS
A16: Prepayment Feb24 expense = 3,300 | B16: =SUM(Prepayments_Schedule!I2:I6) -> 3300 | C16: =IF(B16=3300,"PASS","FAIL") -> PASS
A17: Prepayment remaining balance = 19,700 | B17: =SUM(Prepayments_Schedule!J2:J6) -> 19700 | C17: =IF(B17=19700,"PASS","FAIL") -> PASS

Sheet Journal_Entries
A1: Journal_ID | B1: Date | C1: Journal_Type | D1: Account | E1: Debit | F1: Credit | G1: Description | H1: Source | J1: Cell | K1: Text / Formula
A2: JE001 | B2: 45346 | C2: AP Invoice Recognition | D2: Operating Expenses / Purchases | E2: 132825 | F2: 0 | G2: Recognise supplier invoices raised during the reporting period | H2: AP invoices | J2: Total Debits | K2: =SUM(E:E) -> 416825
A3: JE001 | B3: 45346 | C3: AP Invoice Recognition | D3: Accounts Payable | E3: 0 | F3: 132825 | G3: Recognise supplier invoices raised during the reporting period | H3: AP invoices | J3: Total Credits | K3: =SUM(F:F) -> 416825
A4: JE002 | B4: 45346 | C4: AR Invoice Recognition | D4: Accounts Receivable | E4: 160200 | F4: 0 | G4: Recognise customer invoices raised during the reporting period | H4: AR invoices | J4: Difference | K4: =K2-K3 -> 0
A5: JE002 | B5: 45346 | C5: AR Invoice Recognition | D5: Sales Revenue | E5: 0 | F5: 160200 | G5: Recognise customer invoices raised during the reporting period | H5: AR invoices | J5: Status | K5: =IF(ROUND(K4,2)=0,"PASS","FAIL") -> PASS
A6: JE003 | B6: 45346 | C6: Supplier Payments | D6: Accounts Payable | E6: 45350 | F6: 0 | G6: Record payments made to suppliers | H6: Payments / Cashbook
A7: JE003 | B7: 45346 | C7: Supplier Payments | D7: Bank | E7: 0 | F7: 45350 | G7: Record payments made to suppliers | H7: Payments / Cashbook
A8: JE004 | B8: 45346 | C8: Customer Receipts | D8: Bank | E8: 63950 | F8: 0 | G8: Record cash received from customers | H8: Payments / Cashbook
A9: JE004 | B9: 45346 | C9: Customer Receipts | D9: Accounts Receivable | E9: 0 | F9: 63950 | G9: Record cash received from customers | H9: Payments / Cashbook
A10: JE005 | B10: 45346 | C10: Accruals | D10: Operating Expenses | E10: 11200 | F10: 0 | G10: Record month-end accrued expenses for utilities, professional fees, cleaning, marketing and logistics | H10: Accruals Schedule
A11: JE005 | B11: 45346 | C11: Accruals | D11: Accrued Expenses | E11: 0 | F11: 11200 | G11: Record month-end accrued expenses for utilities, professional fees, cleaning, marketing and logistics | H11: Accruals Schedule
A12: JE006 | B12: 45346 | C12: Prepayment Amortisation | D12: Operating Expenses | E12: 3300 | F12: 0 | G12: Release February prepaid expense to profit and loss | H12: Prepayments Schedule
A13: JE006 | B13: 45346 | C13: Prepayment Amortisation | D13: Prepaid Expenses | E13: 0 | F13: 3300 | G13: Release February prepaid expense to profit and loss | H13: Prepayments Schedule

Sheet Accruals_Schedule
A1: Accrual_ID | B1: Supplier_ID | C1: Supplier_Name | D1: Expense_Type | E1: Period | F1: Accrued_Amount | G1: Journal_ID | H1: Reversal_Date | I1: Status
A2: ACC001 | B2: SUP011 | C2: Metro Utilities Ltd | D2: Utilities | E2: 46077 | F2: 2200 | G2: JE005 | H2: 45352 | I2: Open
A3: ACC002 | B3: SUP016 | C3: Apex Professional Services | D3: Professional Fees | E3: 46077 | F3: 3500 | G3: JE005 | H3: 45352 | I3: Open
A4: ACC003 | B4: SUP014 | C4: BrightClean Facilities | D4: Cleaning | E4: 46077 | F4: 950 | G4: JE005 | H4: 45352 | I4: Open
A5: ACC004 | B5: SUP018 | C5: MediaEdge Marketing Ltd | D5: Marketing | E5: 46077 | F5: 1800 | G5: JE005 | H5: 45352 | I5: Open
A6: ACC005 | B6: SUP013 | C6: Prime Logistics Services | D6: Logistics | E6: 46077 | F6: 2750 | G6: JE005 | H6: 45352 | I6: Open
E8: Total Accruals | F8: =SUM(F2:F6) -> 11200

Sheet Prepayments_Schedule
A1: Prepayment_ID | B1: Supplier_ID | C1: Supplier_Name | D1: Description | E1: Start_Date | F1: End_Date | G1: Total_Prepaid | H1: Monthly_Expense | I1: Feb24_Expense | J1: Remaining_Balance | K1: Journal_ID | L1: Status
A2: PRE001 | B2: SUP015 | C2: Shield Insurance Brokers | D2: Annual insurance prepaid | E2: 45323 | F2: 45688 | G2: 7200 | H2: 600 | I2: 600 | J2: 6600 | K2: JE006 | L2: Active
A3: PRE002 | B3: SUP012 | C3: CloudWorks Software Ltd | D3: Software subscription prepaid | E3: 45323 | F3: 45688 | G3: 6000 | H3: 500 | I3: 500 | J3: 5500 | K3: JE006 | L3: Active
A4: PRE003 | B4: SUP016 | C4: Apex Professional Services | D4: Advisory retainer prepaid | E4: 45323 | F4: 45504 | G4: 4800 | H4: 800 | I4: 800 | J4: 4000 | K4: JE006 | L4: Active
A5: PRE004 | B5: SUP014 | C5: BrightClean Facilities | D5: Cleaning contract prepaid | E5: 45323 | F5: 45412 | G5: 1800 | H5: 600 | I5: 600 | J5: 1200 | K5: JE006 | L5: Active
A6: PRE005 | B6: SUP018 | C6: MediaEdge Marketing Ltd | D6: Campaign fee prepaid | E6: 45323 | F6: 45443 | G6: 3200 | H6: 800 | I6: 800 | J6: 2400 | K6: JE006 | L6: Active
H8: Total Feb24 Expense | I8: =SUM(I2:I6) -> 3300
I9: Total Remaining Balance | J9: =SUM(J2:J6) -> 19700

Sheet Pivot_Reports
A1: Age_Bucket | B1: (All) | E1: Age_Bucket | F1: (All)
A3: Supplier_Name | B3: AP Outstanding | E3: Customer_Name | F3: AR Outstanding | I3: Invoice Count | J3: Type
A4: ABC Office Supplies | B4: 1450 | E4: Blue Retail | F4: 8200 | I4: Status | J4: AP | K4: AR | L4: Grand Total
A5: Apex Consulting | B5: 4650 | E5: BluePeak Retail Group | F5: 4250 | I5: Closed | J5: 16 | K5: 15 | L5: 31
A6: Apex Professional Services | B6: 2900 | E6: City Market | F6: 4400 | I6: Open | J6: 32 | K6: 18 | L6: 50
A7: Bright Marketing | B7: 2150 | E7: ClearView Corporate Ltd | F7: 14500 | I7: Partially Paid | J7: 12 | K7: 17 | L7: 29
A8: BrightClean Facilities | B8: 1900 | E8: Horizon Online Stores | F8: 3200 | I8: Grand Total | J8: 60 | K8: 50 | L8: 110
A9: CloudWorks Software Ltd | B9: 950 | E9: Mega Distributors | F9: 2450
A10: Delta Logistics | B10: 15300 | E10: Nova Electronics | F10: 5100
A11: Global IT Services | B11: 8450 | E11: Nova Wholesale Ltd | F11: 6350
A12: Green Energy Co | B12: 4000 | E12: Prime Wholesale | F12: 15150 | I12: Type | J12: Cash Outflow | K12: Cash Inflow
A13: GreenOffice Supplies | B13: 2500 | E13: Retail Hub | F13: 1650 | I13: Opening | J13: 0 | K13: 5000
A14: MediaEdge Marketing Ltd | B14: 7700 | E14: Smart Retail | F14: 8000 | I14: Payment | J14: 45350 | K14: 0
A15: Metro Utilities Ltd | B15: 2025 | E15: Tech Bazaar | F15: 8300 | I15: Receipt | J15: 0 | K15: 63950
A16: Prime Logistics Services | B16: 7600 | E16: Urban Stores | F16: 4500 | I16: Grand Total | J16: 45350 | K16: 68950
A17: Rapid Transport | B17: 900 | E17: Value Stores | F17: 10200
A18: Secure Systems | B18: 4250 | E18: Grand Total | F18: 96250
A19: Shield Insurance Brokers | B19: 9700
A20: Smart Packaging | B20: 6600
A21: Tech Hardware Ltd | B21: 4450
A22: Grand Total | B22: 87475

Sheet Dashboard
A1: Tesco 2024 Finance Operations Dashboard
A3: KPI | B3: Value | D3: Control Status
A4: Total Invoices | B4: =Summary!B3 -> 110 | D4: Failed Checks | E4: =COUNTIF('Control_Checks sheet'!C:C,"FAIL") -> 0
A5: Total Invoice Amount | B5: =Summary!B4 -> 293025 | D5: Overall Status | E5: =IF(E4=0,"PASS","FAIL") -> PASS
A6: Total Paid Amount | B6: =Summary!B5 -> 109300
A7: Total Outstanding Balance | B7: =Summary!B6 -> 183725
A8: Open Invoices | B8: =Summary!B7 -> 50
A9: Partially Paid Invoices | B9: =Summary!B8 -> 29
A10: Closed Invoices | B10: =Summary!B9 -> 31
A11: AP Outstanding | B11: =Summary!B11 -> 87475
A12: AR Outstanding | B12: =Summary!B12 -> 96250
A13: Cashbook Closing Balance | B13: {=LOOKUP(2,1/(Cashbook!F:F<>""),Cashbook!F:F)} -> 23600
A14: Accruals | B14: =SUM(Accruals_Schedule!F2:F6) -> 11200
A15: Prepayment Feb24 Expense | B15: =SUM(Prepayments_Schedule!I2:I6) -> 3300
A16: Prepayment Remaining Balance | B16: =SUM(Prepayments_Schedule!J2:J6) -> 19700
A18: Source Note
A19: Tesco PLC 2024 Annual Report used as public company reference. Invoice-level AP, AR, payments, cashbook, aging, journals, accruals, and prepayments are modelled for portfolio analysis.
